LICENSE
README.md
example.ipynb
pyproject.toml
data/bubble_0.tif
data/bubble_1.tif
data/bubble_2.tif
data/bubble_3.tif
evosegment/__init__.py
evosegment/clustering.py
evosegment/evoSegment.py.bk
evosegment/labelling.py
evosegment/pickClusters.py
evosegment/utils.py
evosegment-0.0.8.dist-info/METADATA
evosegment-0.0.8.dist-info/WHEEL
evosegment-0.0.8.dist-info/licenses/LICENSE
evosegment-0.0.8.dist-info/RECORD
