Metadata-Version: 2.4
Name: evosegment
Version: 0.0.8
Summary: A tool for segmentation of grayscale evolution from 4D tomograhphy data (or other images)
Project-URL: Documentation, https://gitlab.com/jhektor/evoSegment#readme
Project-URL: Issues, https://gitlab.com/jhektor/evoSegment/-/issues
Project-URL: Source, https://gitlab.com/jhektor/evoSegment
Author-email: Johan Hektor <johan.hektor@mau.se>
License:                     GNU GENERAL PUBLIC LICENSE
License-File: LICENSE
Classifier: Development Status :: 4 - Beta
Classifier: License :: OSI Approved :: GNU General Public License v3 (GPLv3)
Classifier: Programming Language :: Python
Classifier: Programming Language :: Python :: Implementation :: CPython
Classifier: Programming Language :: Python :: Implementation :: PyPy
Requires-Python: >=3.7
Requires-Dist: colorcet
Requires-Dist: fast-histogram
Requires-Dist: matplotlib
Requires-Dist: numpy
Requires-Dist: scipy
Requires-Dist: seaborn
Requires-Dist: tifffile
